django_price
